{
  "news": [
    {
      "id": "8ccfbd94-4697-4b8d-942d-2e084c132bda",
      "headline": "Beeinträchtigungen zwischen Regensburg Hbf und Plattling",
      "newsType": "Reparatur an der Weiche",
      "timePeriod": "Bis voraussichtlich Mittwoch, 23.03.2022 in den frühen Morgenstunden",
      "introText": "<p>Aufgrund einer Reparatur an der Weiche zwischen Regensburg Hbf und Plattling kommt es derzeit zu Beeintr&auml;chtigungen im Fernverkehr der Deutschen Bahn. Da der betroffene Streckenabschnitt nur eingleisig befahrbar ist, versp&auml;ten sich die Z&uuml;ge um etwa 30 Minuten.</p>\n",
      "connectionsHeadline": "Betroffen sind folgende Verbindungen im Fernverkehr:",
      "connections": [
        "Alle ICE, IC, NJ - Züge zwischen Regensburg Hbf und Passau Hbf"
      ],
      "closingText": "<p>Unser Personal vor Ort arbeitet an der St&ouml;rungsbeseitigung. Sobald uns neue Informationen vorliegen, werden wir Sie an dieser Stelle auf dem Laufenden halten.</p>\n\n<p>Bitte informieren Sie sich nochmals vor Reiseantritt &uuml;ber Ihre Verbindung auf <a href=\"https://reiseauskunft.bahn.de\" target=\"_blank\">www.bahn.de/reiseauskunft</a>, im&nbsp;<a href=\"https://c00.adobe.com/v3/49929e9f-38d4-43ce-adbb-321b4c936bd4/start?a_dl=598094fdf1f7dfa61a60a20b&amp;ctxa.launch.campaign.trackingcode=?dbkanal_007=L01_S01_D001_KIN0057_-_bahndeaktuell_LZ06\" target=\"_blank\">DB Navigator</a> oder bei der telefonischen Reiseauskunft Tel. +49 (0)30 2970.</p>\n",
      "priority": "2",
      "distance": [
        "longDistance"
      ],
      "areas": [
        "bw",
        "by",
        "be",
        "br",
        "hb",
        "hh",
        "he",
        "mv",
        "ni",
        "nw",
        "rp",
        "sl",
        "sn",
        "st",
        "sh",
        "th"
      ],
      "lastModified": "22.03.2022 14:37",
      "author": "fernverkehr_ag",
      "expand": false,
      "priorityValue": 316
    },
    {
      "id": "20f4dede-fd99-484e-adab-3b386ff174cc",
      "headline": "Beeinträchtigungen zwischen Köln und Bonn",
      "newsType": "Reparatur an einem Signal",
      "timePeriod": "Heute, 22.03.2022 bis in die Abendstunden",
      "introText": "<p>Aufgrund einer Reparatur an einem Signal zwischen K&ouml;ln und Bonn kommt es im Fernverkehr der Deutschen Bahn derzeit zu Versp&auml;tungen von etwa 25 Minuten im betroffenen Streckenabschnitt.&nbsp;</p>\n",
      "connectionsHeadline": "Betroffen sind folgende Verbindungen im Fernverkehr:",
      "connections": [
        "ICE, IC/EC Züge zwischen Köln und Koblenz, über Bonn",
        "ICE Züge von und nach Berlin, enden und beginnen bereits in Köln Hbf, der Halt Bonn Hbf entfällt"
      ],
      "closingText": "<p>Unser Personal vor Ort arbeitet an der St&ouml;rungsbeseitigung. Sobald uns neue Informationen vorliegen, werden wir Sie an dieser Stelle auf dem Laufenden halten.</p>\n\n<p>Bitte informieren Sie sich nochmals vor Reiseantritt &uuml;ber Ihre Verbindung auf <a href=\"https://reiseauskunft.bahn.de\" target=\"_blank\">www.bahn.de/reiseauskunft</a>, im&nbsp;<a href=\"https://c00.adobe.com/v3/49929e9f-38d4-43ce-adbb-321b4c936bd4/start?a_dl=598094fdf1f7dfa61a60a20b&amp;ctxa.launch.campaign.trackingcode=?dbkanal_007=L01_S01_D001_KIN0057_-_bahndeaktuell_LZ06\" target=\"_blank\">DB Navigator</a> oder bei der telefonischen Reiseauskunft Tel. +49 (0)30 2970.</p>\n",
      "priority": "2",
      "distance": [
        "longDistance"
      ],
      "areas": [
        "bw",
        "by",
        "be",
        "br",
        "hb",
        "hh",
        "he",
        "mv",
        "ni",
        "nw",
        "rp",
        "sl",
        "sn",
        "st",
        "sh",
        "th"
      ],
      "lastModified": "22.03.2022 17:31",
      "author": "fernverkehr_ag",
      "expand": false,
      "priorityValue": 316
    },
    {
      "id": "59f1914c-b2a3-4b15-858a-224a826ca43a",
      "headline": "Beeinträchtigungen zwischen Frankfurt(M) und Mainz",
      "newsType": "Bauarbeiten",
      "timePeriod": "Am Dienstag, 22.03.2022 bis in die Nachtstunden",
      "introText": "<p>Aufgrund von Bauarbeiten auf der Strecke Mainz - Frankfurt(M) Flughafen ist der Fernverkehr der Deutschen Bahn derzeit beeintr&auml;chtigt. Es kommt zu Zugausf&auml;llen.</p>\n",
      "connectionsHeadline": "Betroffen sind folgende Verbindungen im Fernverkehr:",
      "connections": [
        "Einzelne ICE-Züge in/aus Richtung Erfurt/Leipzig/Dresden, die in Wiesbaden Hbf beginnen bzw. enden, fallen zwischen Wiesbaden und Frankfurt(M) aus. Die Halte Wiesbaden Hbf, Mainz Hbf und Frankfurt(M) Flughafen entfallen bei diesen."
      ],
      "closingText": "<p>Die Ausf&auml;lle sind in die Auskunftsmedien eingearbeitet.</p>\n\n<p>Sobald uns neue Informationen vorliegen, werden wir Sie an dieser Stelle auf dem Laufenden halten.</p>\n\n<p>Bitte informieren Sie sich nochmals vor Reiseantritt &uuml;ber Ihre Verbindung auf <a href=\"https://reiseauskunft.bahn.de\" target=\"_blank\">www.bahn.de/reiseauskunft</a>, im&nbsp;<a href=\"https://c00.adobe.com/v3/49929e9f-38d4-43ce-adbb-321b4c936bd4/start?a_dl=598094fdf1f7dfa61a60a20b&amp;ctxa.launch.campaign.trackingcode=?dbkanal_007=L01_S01_D001_KIN0057_-_bahndeaktuell_LZ06\" target=\"_blank\">DB Navigator</a> oder bei der telefonischen Reiseauskunft Tel. +49 (0)30 2970.</p>\n",
      "priority": "2",
      "distance": [
        "longDistance"
      ],
      "areas": [
        "he",
        "rp"
      ],
      "lastModified": "22.03.2022 11:19",
      "author": "fernverkehr_ag",
      "expand": false,
      "priorityValue": 302
    },
    {
      "id": "e69a497b-85da-4812-a86e-a7a5176254b6",
      "headline": "Informationen für Ukraine-Flüchtlinge zur Ein- und Weiterreise ",
      "newsType": "Informationen",
      "introText": "<p>Gefl&uuml;chtete mit ukrainischem Reisepass oder Personalausweis k&ouml;nnen seit dem 1. M&auml;rz 2022 &uuml;ber Polen, Tschechien und &Ouml;sterreich alle Fernverkehrsz&uuml;ge ab der deutschen Grenze kostenfrei bis nach Berlin, Dresden, N&uuml;rnberg und M&uuml;nchen nutzen.</p>\n\n<p>Um die Weiterreise innerhalb Deutschlands zu erleichtern, gibt es das Ticket &bdquo;helpukraine&ldquo;. Dieses erhalten ukrainische Gefl&uuml;chtete in allen Reisezentren in Deutschland.</p>\n\n<p>Alle weiteren Informationen finden Sie unter<a href=\"https://www.bahn.de/helpukraine\">&nbsp;bahn.de/helpukraine</a></p>\n",
      "connections": [],
      "priority": "1",
      "distance": [
        "longDistance"
      ],
      "areas": [
        "bw",
        "by",
        "be",
        "br",
        "hb",
        "hh",
        "he",
        "mv",
        "ni",
        "nw",
        "rp",
        "sl",
        "sn",
        "st",
        "sh",
        "th"
      ],
      "lastModified": "17.03.2022 15:07",
      "author": "fernverkehr_ag",
      "expand": false,
      "priorityValue": 216
    },
    {
      "id": "d29584f5-01ee-4f9f-9628-662131caa507",
      "headline": "Verspätungen und Zugausfälle",
      "newsType": "Feuerwehreinsatz und Reparatur an der Strecke",
      "timePeriod": "bis voraussichtlich 22. März 2022  18:00 Uhr",
      "connectionsHeadline": "folgende Linie ist betroffen:",
      "connections": [
        "RE1 Magdeburg-Potsdam- Berlin - Frankfurt (Oder) - Eisenhüttenstadt - Cottbus"
      ],
      "download": {
        "text": "<p>Aufgrund eines Feuerwehreinsatzes und resultierenden Reparaturarbeiten an der Strecke werden die Z&uuml;ge der Linie RE1 von/nach Magdeburg Hbf &uuml;ber Berlin-Lichtenberg (Zusatzhalt) und Berlin-Gesundbrunnen (Zusatzhalt) und die Z&uuml;ge von/nach Brandenburg Hbf &uuml;ber Berlin Gesundbrunnen(Zusatzhalt) und Berlin Hohensch&ouml;nhausen(Zusatzhalt) umgeleitet.</p>\n\n<p>Die Halte Berlin Ostkreuz, Berlin Ostbahnhof, Berlin Alexanderplatz, Berlin Friedrichstra&szlig;e, Berlin Hbf, Berlin Zoologischer Garten und Berlin-Charlottenburg entfallen.</p>\n\n<p>Es kann zu Versp&auml;tungen und Teilausf&auml;llen kommen.&nbsp;</p>\n"
      },
      "closingText": "<p>Bitte informieren Sie sich unmittelbar vor Reiseantritt &uuml;ber Ihre tats&auml;chlichen Abfahrts- und Ankunftszeiten in der Reiseauskunft unter <a href=\"https://www.bahn.de/\">bahn.de/reiseauskunft</a>, in der App&nbsp;<a href=\"https://www.bahn.de/service/mobile/streckenagent-app\" target=\"_blank\">DB Streckenagent</a>&nbsp;und im&nbsp;<a href=\"https://www.bahn.de/service/mobile/db-navigator\" target=\"_blank\">DB Navigator</a>&nbsp;oder pers&ouml;nlich unter <a href=\"tel:03312356881 \">0331 235 6881 </a>und<a href=\"tel: 0385 750 2405 \">&nbsp;0385 750 2405</a>.&nbsp; &nbsp;&nbsp; &nbsp; &nbsp; &nbsp; &nbsp; &nbsp; &nbsp; &nbsp; &nbsp; &nbsp;</p>\n",
      "priority": "0",
      "distance": [
        "regional"
      ],
      "areas": [
        "be",
        "br",
        "st"
      ],
      "lastModified": "22.03.2022 07:53",
      "expand": false,
      "priorityValue": 103
    },
    {
      "id": "4f14c07f-5966-4c81-9373-59abeec3cc63",
      "headline": "Ausfall der Kulturzüge",
      "newsType": "Beförderung von Flüchtlingen aus der Ukraine",
      "timePeriod": "18.bis vsl. 27.März 2022",
      "introText": "<p>Die Fahrzeuge werden vor&uuml;bergehend f&uuml;r die Bef&ouml;rderung von Fl&uuml;chtenden aus der Ukraine eingesetzt. F&uuml;r Fahrten nach und in Polen verf&uuml;gen nur wenige Fahrzeuge in Deutschland &uuml;ber die technische Voraussetzung &nbsp;Die Fahrzeuge dieser Linie z&auml;hlen dazu, wir arbeiten aber mit Hochdruck an Ersatzfahrzeugen aus anderen Netzen in Deutschland. Wir bitten um Verst&auml;ndnis und etwas Geduld. Vielen Dank!</p>\n\n<p>&nbsp;</p>\n",
      "connectionsHeadline": "IRE Berlin-Lichtenberg - Forst(Lausitz) - Wroclaw Glowny",
      "connections": [],
      "closingText": "<p>Folgende Z&uuml;ge sind vom Ausfall betroffen.</p>\n\n<p><u><strong>am 18.und 25. M&auml;rz 2022</strong></u></p>\n\n<p><strong>IRE5839 </strong>planm&auml;&szlig;ige Abfahrt in Berlin-Lichtenberg um 13:46 Uhr nach Wroclaw Glowny</p>\n\n<p><strong>IRE5838&nbsp;</strong>planm&auml;&szlig;ige Abfahrt in Wroclaw Glowny um 20:11 Uhr nach Berlin-Lichtenberg</p>\n\n<p><u><strong>am 19. und 26.M&auml;rz 2022</strong></u></p>\n\n<p><strong>IRE5837&nbsp;</strong>planm&auml;&szlig;ige Abfahrt in Berlin-Lichtenberg um 08:26 Uhr nach Wroclaw Glowny</p>\n\n<p><u><strong>am 20. und 27.M&auml;rz 2022</strong></u></p>\n\n<p><strong>IRE5836&nbsp;</strong>planm&auml;&szlig;ige Abfahrt in Wroclaw Glowny um 17:32 Uhr nach Berlin-Lichtenberg</p>\n\n<p>Bitte wenden Sie sich bei Erstattungsanspr&uuml;chen an das Servicecenter Fahrgastrechte www.bahn.de/fahrgastrechte.</p>\n\n<p>Informieren Sie sich weiterhin unmittelbar vor Reiseantritt &uuml;ber Ihre tats&auml;chlichen Abfahrts- und Ankunftszeiten in der Reiseauskunft unter <a href=\"https://www.bahn.de/\" style=\"color:blue; text-decoration:underline\">bahn.de/reiseauskunft</a>, in der App&nbsp;<a href=\"https://www.bahn.de/service/mobile/streckenagent-app\" target=\"_blank\">DB Streckenagent</a>&nbsp;und im&nbsp;<a href=\"https://www.bahn.de/service/mobile/db-navigator\" target=\"_blank\">DB Navigator</a>&nbsp;oder pers&ouml;nlich unter 0<strong><a href=\"tel:03312356881\" style=\"color:blue; text-decoration:underline\">331 235-6881</a></strong> und&nbsp;<strong><a href=\"tel:03857502405\" style=\"color:blue; text-decoration:underline\">0385 750-2405</a>&nbsp;</strong>.</p>\n",
      "priority": "0",
      "distance": [
        "regional"
      ],
      "areas": [
        "be",
        "br"
      ],
      "lastModified": "18.03.2022 11:05",
      "author": "nordost",
      "expand": false,
      "priorityValue": 102
    },
    {
      "id": "e6e505da-4a29-4d59-8acf-745c89b41143",
      "headline": "Ausfall der Linie RB66 / RE66",
      "newsType": "Beförderung von Flüchtlingen aus der Ukraine",
      "timePeriod": "21. bis 27. März 2022",
      "introText": "<p>Fast alle Z&uuml;ge der Linie RE/RB66 fallen vom 21.- 27. M&auml;rz 2022 weiterhin aus und es wird Ersatzverkehr eingerichtet. Seit dem 07.03.2022 besteht bereits ein ver&auml;ndertes Fahrplanangebot aufgrund von Bauarbeiten (Gleisbauarbeiten) zwischen Angerm&uuml;nde und Passow (Uckerm).&nbsp;Da wir baubedingt aktuell nicht durchgehend fahren k&ouml;nnen, werden deshalb vor&uuml;bergehend&nbsp;die f&uuml;r den Verkehr nach Polen zugelassenen Fahrzeuge f&uuml;r die Bef&ouml;rderung von Fl&uuml;chtenden aus der Ukraine eingesetzt. Grund ist, dass nur wenige Fahrzeuge in Deutschland&nbsp;&uuml;ber die daf&uuml;r erforderlichen technischen Voraussetzungen&nbsp;verf&uuml;gen. Die Fahrzeuge dieser Linie z&auml;hlen dazu. Wir bitten Sie um Ihr Verst&auml;ndnis und danken Ihnen, dass Sie somit&nbsp;unsere Bem&uuml;hungen zur Evakuierung der Fl&uuml;chtenden unterst&uuml;tzen.</p>\n",
      "connections": [
        "RB66/RE66 Berlin - Angermünde - Szczecin Glowny"
      ],
      "download": {
        "text": "<p>Den Fahrplan f&uuml;r den Ersatzverkehr finden Sie hier:</p>\n",
        "linkDataList": [
          {
            "link": "https://assets.static-bahn.de/dam/jcr:7494c69e-00cf-44b6-8b0c-81a908a5d10d/BNV%20RB66%20WA-XPSG%2021.03.-27.03.2022.pdf",
            "title": "Ersatzverkehr RE / RB66 (PDF, 82 KB)",
            "info": "",
            "openInNewTab": false
          },
          {
            "link": "https://assets.static-bahn.de/dam/jcr:9a79a2e3-3d38-4a79-931a-3c4f4ed9c27f/ExpressbusseRB66%20WA-XPSG%2021.03.-27.03.2022.pdf",
            "title": "Expressbusse RE / RB66 (PDF, 58 KB)",
            "info": "",
            "openInNewTab": false
          }
        ]
      },
      "closingText": "<p>Bitte informieren Sie sich unmittelbar vor Reiseantritt &uuml;ber Ihre tats&auml;chlichen Abfahrts- und Ankunftszeiten in der Reiseauskunft unter <a href=\"https://www.bahn.de/\">bahn.de/reiseauskunft</a>, in der App&nbsp;<a href=\"https://www.bahn.de/service/mobile/streckenagent-app\" target=\"_blank\">DB Streckenagent</a>&nbsp;und im&nbsp;<a href=\"https://www.bahn.de/service/mobile/db-navigator\" target=\"_blank\">DB Navigator</a>&nbsp;oder pers&ouml;nlich unter <a href=\"tel:03312356881 \">0331 235 6881 </a>und<a href=\"tel: 0385 750 2405 \">&nbsp;0385 750 2405</a>.</p>\n",
      "priority": "0",
      "distance": [
        "regional"
      ],
      "areas": [
        "be",
        "br"
      ],
      "lastModified": "19.03.2022 11:10",
      "author": "nordost",
      "expand": true,
      "priorityValue": 102
    },
    {
      "id": "3f318b0b-7c89-411a-beac-fdd6d502e3cb",
      "headline": "Meldungen der S-Bahn Berlin",
      "newsType": "Störung",
      "timePeriod": "unbefristet",
      "introText": "<p>Meldungen &uuml;ber die aktuelle Betriebslage der S-Bahn Berlin finden Sie <a href=\"https://sbahn.berlin/fahren/fahrplanaenderungen/\" target=\"_blank\">hier</a>.</p>\n\n<p>Aktuelle Verkehrsmeldungen und Infos der S-Bahn Berlin finden Sie auf dem frei zug&auml;nglichen <a href=\"https://twitter.com/SBahnBerlin\" target=\"_blank\">Twitter-Kanal</a>.</p>\n",
      "connections": [],
      "priority": "0",
      "distance": [
        "regional"
      ],
      "areas": [
        "be",
        "br"
      ],
      "lastModified": "21.03.2022 18:12",
      "author": "nordost",
      "expand": true,
      "priorityValue": 102
    },
    {
      "id": "2ef2f9ec-38c8-4364-b98f-264c06f4f70c",
      "headline": "Vorübergehend reduziertes Fahrplanangebot bei der Westfrankenbahn",
      "newsType": "erhöhter Krankenstand beim Fahrpersonal",
      "timePeriod": "ab Montag, 21. März 2022 bis vsl. Freitag, 25. März 2022",
      "introText": "<p>Aufgrund eines erh&ouml;hten Krankenstandes beim Fahrpersonal kommt es ab Montag, den 21. M&auml;rz bis Freitag, den 25. M&auml;rz 2022 zu Zugausf&auml;llen. Wo es m&ouml;glich ist, haben wir Schienenersatzverkehr f&uuml;r Sie eingerichtet.</p>\n\n<p>Bitte informieren Sie sich tagesaktuell in den Online-Reiseausk&uuml;nften oder &uuml;ber die App DB-Streckenagent.</p>\n",
      "connectionsHeadline": "Die Fahrpläne zum reduzierten Fahrplanangebot finden Sie hier:",
      "connections": [],
      "download": {
        "linkDataList": [
          {
            "link": "https://assets.static-bahn.de/dam/jcr:3780c958-b617-4679-984b-a320e803645b/Hohenlohebahn_reduziertes%20Angebot_KW%2012.pdf",
            "title": "Hohenlohebahn_reduziertes Angebot_KW 12.pdf (PDF, 430 KB)",
            "info": "Crailsheim - Heilbronn (Hohenlohebahn)",
            "openInNewTab": false
          },
          {
            "link": "https://assets.static-bahn.de/dam/jcr:4f2ce7eb-ca8a-4a02-9d52-f55bdaa4d8db/Madonnenlandbahn_reduziertes%20Angebot_KW%2012.pdf",
            "title": "Madonnenlandbahn_reduziertes Angebot_KW 12.pdf (PDF, 417 KB)",
            "info": "Miltenberg - Seckach (Madonnenlandbahn)",
            "openInNewTab": false
          },
          {
            "link": "https://assets.static-bahn.de/dam/jcr:986d2412-8536-4cdd-af5e-dc7c4101b7b5/Maintalbahn_reduziertes%20Angebot_KW%2012.pdf",
            "title": "Maintalbahn_reduziertes Angebot_KW 12.pdf (PDF, 450 KB)",
            "info": "Aschaffenburg - Miltenberg - Wertheim (Maintalbahn)",
            "openInNewTab": false
          },
          {
            "link": "https://assets.static-bahn.de/dam/jcr:bf23cdd3-0a95-4e52-985a-82195fb0f9af/Tauberbahn_reduziertes%20Angebot_KW%2012.pdf",
            "title": "Tauberbahn_reduziertes Angebot_KW 12.pdf (PDF, 461 KB)",
            "info": "Wertheim - Lauda - Crailsheim (Tauberbahn)",
            "openInNewTab": false
          }
        ]
      },
      "closingText": "<p>Bitte ber&uuml;cksichtigen Sie die &Auml;nderungen im Zugverkehr bei Ihrer Reiseplanung und rechnen Sie f&uuml;r die Dauer der Beeintr&auml;chtigung mehr Reisezeit ein.<br />\n<br />\nImmer sofort informiert &uuml;ber St&ouml;rungen, Ersatzverkehr und Alternativrouten. Denn Ihren mobilen Zugbegleiter haben Sie mit der neuen&nbsp;<a href=\"https://www.bahn.de/p/view/service/mobile/streckenagent-app.shtml\">Streckenagent-APP</a>&nbsp;immer dabei!</p>\n",
      "priority": "0",
      "distance": [
        "regional"
      ],
      "areas": [
        "bw",
        "by"
      ],
      "lastModified": "17.03.2022 16:54",
      "expand": false,
      "priorityValue": 102
    },
    {
      "id": "d91268e7-0a13-433e-b963-1287e2ec9159",
      "headline": "Meldungen der Südostbayernbahn",
      "newsType": "Störungen",
      "timePeriod": "unbefristet",
      "introText": "<p>Meldungen &uuml;ber die aktuelle Betriebslage des Regionalverkehrs im Verkehrsgebiet der S&uuml;dostbayernbahn finden Sie hier:&nbsp;</p>\n",
      "connections": [],
      "internal": {
        "linkDataList": [
          {
            "link": "https://www.suedostbayernbahn.de/fahrplan/newsticker",
            "title": "Aktuelle Betriebslage",
            "info": "",
            "openInNewTab": true
          }
        ]
      },
      "priority": "0",
      "distance": [
        "regional"
      ],
      "areas": [
        "by"
      ],
      "lastModified": "13.10.2021 08:58",
      "author": "suedostbayernbahn",
      "expand": true,
      "priorityValue": 101
    },
    {
      "id": "4f487598-ca7d-4725-8097-4f6cf1e7824d",
      "headline": "Zugausfälle auf den Linien RE4, RE5, RB17 und S1 am 24. und 25. März 2022 ",
      "newsType": "krankheitsbedingte Personalausfälle",
      "timePeriod": "24. und 25. März 2022",
      "introText": "<p>Auf den Linien RE4, RE5, RB17 und S1 muss das Fahrplanangebot reduziert werden. Einige Z&uuml;ge fallen aus und werden&nbsp;durch Busse ersetzt.</p>\n\n<p>Grund sind hohe krankheitsbedingte Personalausf&auml;lle.</p>\n",
      "connectionsHeadline": "Folgende Linien sind betroffen:",
      "connections": [
        "RE4 Pasewalk - Ueckermünde Stadthafen",
        "RE5 Stralsund - Neustrelitz",
        "RB17 Ludwigslust - Schwerin - Wismar sowie Rostock - Schwerin",
        "S1 Warnemünde - Rostock "
      ],
      "download": {
        "text": "<p><strong>Auf der Linie RE4 fallen am 24. und 25. M&auml;rz 2022 aus:<br />\nRE13271</strong>&nbsp;Pasewalk ab 06:10 Uhr nach Ueckerm&uuml;nde Stadthafen<br />\n<strong>RE13273</strong>&nbsp;Pasewalk ab 08:22 Uhr nach Ueckerm&uuml;nde Stadthafen<br />\n<strong>RE13275</strong>&nbsp;Pasewalk ab 10:22 Uhr nach Ueckerm&uuml;nde Stadthafen<br />\n<strong>RE13277</strong>&nbsp;Pasewalk ab 12:22 Uhr nach Ueckerm&uuml;nde Stadthafen<br />\n<strong>RE13279</strong>&nbsp;Pasewalk ab 14:22 Uhr nach Ueckerm&uuml;nde Stadthafen<br />\n<strong>RE13281</strong>&nbsp;Pasewalk ab 16:08 Uhr nach Ueckerm&uuml;nde Stadthafen<br />\n<strong>RE13283</strong>&nbsp;Pasewalk ab 18:22 Uhr nach Ueckerm&uuml;nde Stadthafen<br />\n<strong>RE13285</strong>&nbsp;Pasewalk ab 20:22 Uhr nach Ueckerm&uuml;nde Stadthafen</p>\n\n<p><strong>RE13270</strong>&nbsp;Ueckerm&uuml;nde Stadthafen ab 07:00 Uhr nach Pasewalk<br />\nR<strong>E13272</strong>&nbsp;Ueckerm&uuml;nde Stadthafen ab 09:00 Uhr nach Pasewalk<br />\n<strong>RE13274</strong>&nbsp;Ueckerm&uuml;nde Stadthafen ab 11:00 Uhr nach Pasewalk<br />\n<strong>RE13276</strong>&nbsp;Ueckerm&uuml;nde Stadthafen ab 13:00 Uhr nach Pasewalk<br />\n<strong>RE13278</strong>&nbsp;Ueckerm&uuml;nde Stadthafen ab 13:00 Uhr nach Pasewalk<br />\n<strong>RE13280</strong>&nbsp;Ueckerm&uuml;nde Stadthafen ab 17:00 Uhr nach Pasewalk<br />\n<strong>RE13282</strong>&nbsp;Ueckerm&uuml;nde Stadthafen ab 19:00 Uhr nach Pasewalk<br />\n<strong>RE13284</strong>&nbsp;Ueckerm&uuml;nde Stadthafen ab 21:00 Uhr nach Pasewalk</p>\n\n<p>Bitte nutzen Sie als Ersatz den bereitgestellten Ersatzverkehr.</p>\n\n<p><strong>Auf der Linie RE5 fallen am 24. und 25. M&auml;rz aus:<br />\nRE13051</strong>&nbsp;Neubrandenburg ab 05:29 Uhr nach Neustrelitz<br />\n<strong>RE13053</strong>&nbsp;Neubrandenburg ab 07:31 Uhr nach Neustrelitz<br />\n<strong>RE13055</strong>&nbsp;Neubrandenburg ab 09:31 Uhr nach Neustrelitz<br />\n<strong>RE13063</strong>&nbsp;Neubrandenburg ab 17:31 Uhr nach Neustrelitz<br />\n<strong>RE13065</strong>&nbsp;Neubrandenburg ab 19:31 Uhr nach Neustrelitz<br />\n<strong>RE13067</strong>&nbsp;Neubrandenburg ab 21:31 Uhr nach Neustrelitz</p>\n\n<p><strong>RE13052</strong>&nbsp;Neustrelitz ab 06:02 Uhr nach Neubrandenburg<br />\n<strong>RE13054</strong>&nbsp;Neustrelitz ab 08:03 Uhr nach Neubrandenburg<br />\n<strong>RE13056</strong>&nbsp;Neustrelitz ab 10:03 Uhr nach Neubrandenburg<br />\n<strong>RE13058</strong> Neustrelitz&nbsp;ab 18:03 Uhr nach Neubrandenburg<br />\n<strong>RE13066</strong>&nbsp;Neustrelitz ab 20:03 Uhr nach Neubrandenburg<br />\n<strong>RE13068</strong>&nbsp;Neustrelitz ab 22:03 Uhr nach Neubrandenburg</p>\n\n<p>Bitte nutzen Sie die nachfolgenden Z&uuml;ge der Linie RE5 von/nach Stralsund und von/nach W&uuml;nsdorf(Waldstadt)/Elsterwerda.&nbsp; &nbsp; &nbsp; &nbsp; &nbsp; &nbsp; &nbsp; &nbsp; &nbsp; &nbsp; &nbsp; &nbsp; &nbsp; &nbsp; &nbsp; &nbsp; &nbsp; &nbsp; &nbsp; &nbsp; &nbsp; &nbsp; &nbsp; &nbsp; &nbsp; &nbsp; &nbsp; &nbsp; &nbsp; &nbsp; &nbsp; &nbsp; &nbsp; &nbsp;&nbsp;</p>\n\n<p><strong>Auf der Linie RB17 fallen am 24. und 25. M&auml;rz 2022 aus:<br />\nRB13150</strong>&nbsp;Ludwigslust ab 04:57 Uhr nach Wismar<br />\n<strong>RB13158</strong>&nbsp;Ludwigslust ab 08:25 Uhr nach Wismar<br />\n<strong>RB13162</strong>&nbsp;Ludwigslust ab 12:25 Uhr nach Wismar<br />\n<strong>RB13170</strong>&nbsp;Ludwigslust ab 16:25 Uhr nach Wismar&nbsp;<br />\n<strong>RB91974 </strong>Schwerin ab 19:04 Uhr nach Wismar &nbsp;&nbsp;&nbsp;&nbsp;&nbsp; <strong>[nur am 25.03.]</strong><br />\n<strong>RB13176</strong>&nbsp;Ludwigslust ab 20:25 Uhr nach Wismar&nbsp;&nbsp;&nbsp;&nbsp;&nbsp;&nbsp;&nbsp;&nbsp;&nbsp;&nbsp;&nbsp;&nbsp;&nbsp;&nbsp;&nbsp;<br />\n<strong>RB91976</strong> Schwerin ab 21:07 Uhr nach Wismar&nbsp; &nbsp; &nbsp; <strong>[nur am 25.03.]</strong><br />\n<strong>RB13180</strong>&nbsp;Ludwigslust ab 23:56 Uhr nach Schwerin Hbf&nbsp;&nbsp;&nbsp;&nbsp;&nbsp;&nbsp;</p>\n\n<p><strong>RB13153</strong>&nbsp;Wismar ab 06:24 Uhr nach Ludwigslust&nbsp;&nbsp;&nbsp;&nbsp;&nbsp;&nbsp;&nbsp;&nbsp;&nbsp;&nbsp;&nbsp;&nbsp;&nbsp;&nbsp;&nbsp;&nbsp;&nbsp;&nbsp;&nbsp;&nbsp;&nbsp;&nbsp;&nbsp;&nbsp;&nbsp;&nbsp;&nbsp;&nbsp;&nbsp;&nbsp;&nbsp;&nbsp;&nbsp;&nbsp;&nbsp;&nbsp;&nbsp;&nbsp;&nbsp;&nbsp;&nbsp;&nbsp;&nbsp;&nbsp;&nbsp;&nbsp;&nbsp;<br />\n<strong>RB13159</strong>&nbsp;Wismar ab 10:24 Uhr nach Ludwigslust<br />\n<strong>RB13163</strong>&nbsp;Wismar ab 14:24 Uhr nach Ludwigslust<br />\n<strong>RB13171</strong>&nbsp;Wismar ab 18:24 Uhr nach Ludwigslust&nbsp;<br />\n<strong>RB91975</strong> Wismar ab 20:24 Uhr nach Schwerin &nbsp;&nbsp;&nbsp;&nbsp;&nbsp;<strong>[nur am 25.03.]</strong>&nbsp;&nbsp;&nbsp;&nbsp;&nbsp;&nbsp;&nbsp;&nbsp;&nbsp; &nbsp;&nbsp;&nbsp;&nbsp;&nbsp;&nbsp;&nbsp;&nbsp;&nbsp;&nbsp;&nbsp;<br />\n<strong>RB13177</strong>&nbsp;Wismar ab 22:24 Uhr nach Ludwigslust<br />\n<strong>RB91977</strong> Wismar ab 22:24 Uhr nach Schwerin&nbsp;&nbsp;&nbsp;&nbsp;&nbsp;<strong>[nur am 25.03.]</strong></p>\n\n<p><strong>RB13169&nbsp;</strong>Rostock Hbf ab 16:09 Uhr nach Ludwigslust</p>\n\n<p>Bitte nutzen Sie die nachfolgenden Z&uuml;ge der Linie RE2 bzw. den Ersatzverkehr.<br />\n<br />\n<strong>Auf der Linie RB17 fallen am 24. und 25. M&auml;rz 2022 aus:</strong><br />\nRE13154 Schwerin ab 06:42 Uhr nach Rostock<br />\nRE13169 Rostock ab 16:09 Uhr nach Schwerin</p>\n\n<p><strong>Auf der Linie S1 fallen vom 22. bis 25.03. aus:</strong><br />\nS33916 Rostock ab 13:25 Uhr nach Warnem&uuml;nde<br />\nS33924 Rostock ab 14:25 Uhr nach Warnem&uuml;nde<br />\nS33917 Warnem&uuml;nde ab 13:56 Uhr nach Rostock<br />\nS33925 Warnem&uuml;nde ab 14:54 Uhr nach Rostock</p>\n",
        "linkDataList": [
          {
            "link": "https://assets.static-bahn.de/dam/jcr:c6f8e275-39b5-422b-b281-ca3012c162e8/20210321%20BNV%20WP-WUMH%20(RE4)%2024.+25.03.2022.pdf",
            "title": "Ersatzverkehr RE4 24._25.3. (PDF, 91 KB)",
            "info": "",
            "openInNewTab": false
          },
          {
            "link": "https://assets.static-bahn.de/dam/jcr:266a1c4a-db8c-4432-a4ed-f3181636eaf7/20220321%20BNV%20Wismar-Ludwigslust%20(RB17)%2024.+25.03.2022.pdf",
            "title": "Ersatzverkehr RB17 24._25.3. (PDF, 91 KB)",
            "info": "",
            "openInNewTab": false
          }
        ]
      },
      "closingText": "<p>Bitte informieren Sie sich unmittelbar vor Reiseantritt &uuml;ber Ihre tats&auml;chlichen Abfahrts- und Ankunftszeiten in der Reiseauskunft unter <a href=\"https://www.bahn.de/\">bahn.de/reiseauskunft</a>, in der App&nbsp;<a href=\"https://www.bahn.de/service/mobile/streckenagent-app\" target=\"_blank\">DB Streckenagent</a>&nbsp;und im&nbsp;<a href=\"https://www.bahn.de/service/mobile/db-navigator\" target=\"_blank\">DB Navigator</a>&nbsp;oder pers&ouml;nlich unter <a href=\"tel:03312356881 \">0331 235 6881 </a>und<a href=\"tel: 0385 750 2405 \">&nbsp;0385 750 2405</a>.&nbsp; &nbsp;&nbsp; &nbsp; &nbsp; &nbsp; &nbsp; &nbsp; &nbsp; &nbsp; &nbsp; &nbsp;</p>\n",
      "priority": "0",
      "distance": [
        "regional"
      ],
      "areas": [
        "mv"
      ],
      "lastModified": "22.03.2022 07:34",
      "author": "nordost",
      "expand": false,
      "priorityValue": 101
    },
    {
      "id": "d0f4937d-ebd1-46de-8f3a-44c483167248",
      "headline": "aktualisiert: Zugausfälle vom 21. bis 23. März 2022 auf den Linien RB17, RE4 und RE5 und neu S1",
      "newsType": "krankheitsbedingte Personalausfälle",
      "timePeriod": "21.bis 23. März 2022",
      "introText": "<p>Auf den Linien RB17, RE4 und RE5 muss das Fahrplanangebot reduziert werden. Einige Z&uuml;ge fallen aus und werden&nbsp;durch Busse ersetzt.</p>\n\n<p>Grund sind hohe krankheitsbedingte Personalausf&auml;lle.</p>\n",
      "connectionsHeadline": "Folgende Linien sind betroffen:",
      "connections": [
        "RB17 Ludwigslust - Schwerin-Wismar",
        "RE4 Pasewalk - Ueckermünde Stadthafen",
        "RE5 Stralsund - Neustrelitz",
        "S1 Warnemünde - Rostock "
      ],
      "download": {
        "text": "<p><strong>Auf der Linie RB17 fallen vom 21. bis 23. M&auml;rz 2022 aus:</strong><br />\nRB13150 Ludwigslust ab 04:57 Uhr nach Wismar&nbsp;<br />\nRB13158 Ludwigslust ab 08:25 Uhr nach Wismar<br />\nRB13162 Ludwigslust ab 12:25 Uhr nach Wismar&nbsp;<br />\nRB13170 Ludwigslust ab 16:25 Uhr nach Wismar&nbsp; &nbsp; &nbsp; &nbsp; &nbsp; &nbsp; &nbsp; &nbsp; &nbsp; &nbsp; &nbsp; &nbsp; &nbsp; &nbsp; &nbsp; &nbsp; &nbsp; &nbsp; &nbsp; &nbsp; &nbsp; &nbsp; &nbsp; &nbsp; &nbsp; &nbsp; &nbsp; &nbsp; &nbsp; &nbsp; &nbsp; &nbsp; &nbsp; &nbsp; &nbsp; &nbsp; &nbsp; &nbsp; &nbsp; &nbsp; &nbsp; &nbsp; &nbsp; &nbsp; &nbsp; &nbsp;<br />\nRB13176 Ludwigslust ab 20:25 Uhr nach Wismar&nbsp; &nbsp; &nbsp; &nbsp; &nbsp; &nbsp; &nbsp; &nbsp; &nbsp; &nbsp; &nbsp; &nbsp; &nbsp; &nbsp; &nbsp; &nbsp; &nbsp; &nbsp; &nbsp; &nbsp; &nbsp; &nbsp; &nbsp; &nbsp; &nbsp; &nbsp; &nbsp; &nbsp; &nbsp; &nbsp; &nbsp; &nbsp; &nbsp; &nbsp; &nbsp; &nbsp; &nbsp; &nbsp; &nbsp; &nbsp; &nbsp; &nbsp; &nbsp; &nbsp; &nbsp;&nbsp;<br />\nRB13180&nbsp;Ludwigslust ab 23:56 nach Schwerin Hbf<br />\n<br />\nRB13153 Wismar ab 06:24 Uhr nach Ludwigslust&nbsp; &nbsp; &nbsp; &nbsp; &nbsp; &nbsp; &nbsp; &nbsp; &nbsp; &nbsp; &nbsp; &nbsp; &nbsp; &nbsp; &nbsp; &nbsp; &nbsp; &nbsp; &nbsp; &nbsp; &nbsp; &nbsp; &nbsp; &nbsp; &nbsp; &nbsp; &nbsp; &nbsp; &nbsp; &nbsp; &nbsp; &nbsp; &nbsp; &nbsp; &nbsp; &nbsp; &nbsp; &nbsp; &nbsp; &nbsp; &nbsp; &nbsp; &nbsp; &nbsp; &nbsp; &nbsp; &nbsp; RB13159 Wismar ab 10:24 Uhr nach Ludwigslust<br />\nRB13163 Wismar ab 14:24 Uhr nach Ludwigslust&nbsp; &nbsp; &nbsp; &nbsp; &nbsp; &nbsp; &nbsp; &nbsp; &nbsp; &nbsp; &nbsp; &nbsp; &nbsp; &nbsp; &nbsp; &nbsp; &nbsp; &nbsp; &nbsp; &nbsp; &nbsp; &nbsp; &nbsp; &nbsp; &nbsp; &nbsp; &nbsp; &nbsp; &nbsp; &nbsp; &nbsp; &nbsp; &nbsp; &nbsp; &nbsp; &nbsp; &nbsp; &nbsp; &nbsp; &nbsp; &nbsp; &nbsp; &nbsp; &nbsp; &nbsp; &nbsp;<br />\nRB13171 Wismar ab 18:24 Uhr&nbsp;nach Ludwigslust&nbsp;&nbsp;&nbsp;&nbsp;&nbsp;&nbsp;&nbsp;&nbsp;&nbsp;&nbsp;&nbsp;&nbsp;&nbsp;&nbsp;&nbsp;&nbsp;&nbsp;&nbsp;&nbsp;&nbsp;&nbsp;&nbsp;&nbsp;&nbsp;&nbsp;&nbsp;&nbsp;&nbsp;&nbsp;&nbsp;&nbsp;&nbsp;&nbsp;&nbsp;&nbsp;&nbsp;&nbsp;&nbsp;&nbsp;&nbsp;&nbsp;&nbsp;&nbsp;&nbsp;&nbsp;&nbsp;&nbsp;&nbsp;&nbsp;&nbsp;&nbsp;&nbsp;&nbsp;&nbsp;&nbsp;&nbsp;&nbsp;&nbsp;&nbsp;&nbsp;&nbsp;&nbsp;&nbsp;&nbsp;&nbsp;&nbsp;&nbsp;&nbsp;&nbsp;&nbsp;&nbsp;&nbsp;&nbsp;&nbsp;&nbsp;&nbsp;&nbsp;&nbsp;&nbsp;&nbsp;&nbsp;&nbsp;&nbsp;&nbsp;&nbsp;&nbsp;&nbsp;&nbsp;&nbsp;&nbsp;&nbsp;&nbsp;<br />\nRB13177&nbsp;Wismar ab 22:24 Uhr&nbsp;nach Ludwigslust</p>\n\n<p>RB13154 Schwerin Hbf ab 06:42 Uhr nach Rostock Hbf&nbsp; &nbsp; &nbsp; &nbsp; &nbsp; &nbsp; &nbsp; &nbsp; &nbsp; &nbsp; &nbsp; &nbsp; &nbsp; &nbsp; &nbsp; &nbsp; &nbsp; &nbsp; &nbsp; &nbsp; &nbsp; &nbsp; &nbsp; &nbsp; &nbsp; &nbsp; &nbsp; &nbsp; &nbsp; &nbsp; &nbsp; &nbsp; &nbsp; &nbsp; &nbsp; &nbsp; &nbsp; &nbsp; &nbsp; &nbsp; &nbsp; RB13169 Rostock Hbf ab 16:09 Uhr nach Ludwigslust</p>\n\n<p>Bitte nutzen Sie die nachfolgenden Z&uuml;ge der Linie RE2 bzw. den Busnotverkehr.</p>\n\n<p><strong>Auf der Linie RE Linie 5 fallen vom 21.03. bis 23.M&auml;rz aus:</strong><br />\nRE13051 Neubrandenburg ab 05:29 Uhr nach Neustrelitz&nbsp;&nbsp;&nbsp;&nbsp;&nbsp;&nbsp;&nbsp;&nbsp;&nbsp;&nbsp;&nbsp;&nbsp;&nbsp;&nbsp;&nbsp;&nbsp;&nbsp;&nbsp;&nbsp;&nbsp;&nbsp;&nbsp;&nbsp;&nbsp;&nbsp;&nbsp;&nbsp;&nbsp;&nbsp;&nbsp;&nbsp;&nbsp;&nbsp;&nbsp;&nbsp;&nbsp;&nbsp;&nbsp;&nbsp;&nbsp;&nbsp;&nbsp;&nbsp;&nbsp;&nbsp;&nbsp;&nbsp;&nbsp;&nbsp;&nbsp;&nbsp;&nbsp;&nbsp;&nbsp;&nbsp;&nbsp;&nbsp;&nbsp;&nbsp;&nbsp;&nbsp;&nbsp;&nbsp;&nbsp;&nbsp;&nbsp;&nbsp;&nbsp;&nbsp;&nbsp;&nbsp;&nbsp;&nbsp;&nbsp;&nbsp;&nbsp;&nbsp;&nbsp;&nbsp;&nbsp;<br />\nRE13053 Neubrandenburg ab 07:31 Uhr nach Neustrelitz&nbsp;&nbsp;&nbsp;&nbsp;&nbsp;&nbsp;&nbsp;&nbsp;&nbsp;&nbsp;&nbsp;&nbsp;&nbsp;&nbsp;&nbsp;&nbsp;&nbsp;&nbsp;&nbsp;&nbsp;&nbsp;&nbsp;&nbsp;&nbsp;&nbsp;&nbsp;&nbsp;&nbsp;&nbsp;&nbsp;&nbsp;&nbsp;&nbsp;&nbsp;&nbsp;&nbsp;&nbsp;&nbsp;&nbsp;&nbsp;&nbsp;&nbsp;&nbsp;&nbsp;&nbsp;&nbsp;&nbsp;&nbsp;&nbsp;&nbsp;&nbsp;&nbsp;&nbsp;&nbsp;&nbsp;&nbsp;&nbsp;&nbsp;&nbsp;&nbsp;&nbsp;&nbsp;&nbsp;&nbsp;&nbsp;&nbsp;&nbsp;&nbsp;&nbsp;&nbsp;&nbsp;&nbsp;&nbsp;&nbsp;&nbsp;&nbsp;&nbsp;&nbsp;&nbsp;&nbsp;<br />\nRE13055 Neubrandenburg ab 09:31 Uhr nach Neustrelitz&nbsp;&nbsp;&nbsp;&nbsp;&nbsp;&nbsp;&nbsp;&nbsp;&nbsp;&nbsp;&nbsp;&nbsp;&nbsp;&nbsp;&nbsp;&nbsp;&nbsp;&nbsp;&nbsp;&nbsp;&nbsp;&nbsp;&nbsp;&nbsp;&nbsp;&nbsp;&nbsp;&nbsp;&nbsp;&nbsp;&nbsp;&nbsp;&nbsp;&nbsp;&nbsp;&nbsp;&nbsp;&nbsp;&nbsp;&nbsp;&nbsp;&nbsp;&nbsp;&nbsp;&nbsp;&nbsp;&nbsp;&nbsp;&nbsp;&nbsp;&nbsp;&nbsp;&nbsp;&nbsp;&nbsp;&nbsp;&nbsp;&nbsp;&nbsp;&nbsp;&nbsp;&nbsp;&nbsp;&nbsp;&nbsp;&nbsp;&nbsp;&nbsp;&nbsp;&nbsp;&nbsp;&nbsp;&nbsp;&nbsp;&nbsp;&nbsp;&nbsp;&nbsp;&nbsp;&nbsp;<br />\nRE13063 Neubrandenburg ab 17:31 Uhr nach Neustrelitz&nbsp;&nbsp;&nbsp;&nbsp;&nbsp;&nbsp;&nbsp;&nbsp;&nbsp;&nbsp;&nbsp;&nbsp;&nbsp;&nbsp;&nbsp;&nbsp;&nbsp;&nbsp;&nbsp;&nbsp;&nbsp;&nbsp;&nbsp;&nbsp;&nbsp;&nbsp;&nbsp;&nbsp;&nbsp;&nbsp;&nbsp;&nbsp;&nbsp;&nbsp;&nbsp;&nbsp;&nbsp;&nbsp;&nbsp;&nbsp;&nbsp;&nbsp;&nbsp;&nbsp;&nbsp;&nbsp;&nbsp;&nbsp;&nbsp;&nbsp;&nbsp;&nbsp;&nbsp;&nbsp;&nbsp;&nbsp;&nbsp;&nbsp;&nbsp;&nbsp;&nbsp;&nbsp;&nbsp;&nbsp;&nbsp;&nbsp;&nbsp;&nbsp;&nbsp;&nbsp;&nbsp;&nbsp;&nbsp;&nbsp;&nbsp;&nbsp;<br />\nRE13065 Neubrandenburg ab 19:31 Uhr nach Neustrelitz&nbsp;&nbsp;&nbsp;&nbsp;&nbsp;&nbsp;&nbsp;&nbsp;&nbsp;&nbsp;&nbsp;&nbsp;&nbsp;&nbsp;&nbsp;&nbsp;&nbsp;&nbsp;&nbsp;&nbsp;&nbsp;&nbsp;&nbsp;&nbsp;&nbsp;&nbsp;&nbsp;&nbsp;&nbsp;&nbsp;&nbsp;&nbsp;&nbsp;&nbsp;&nbsp;&nbsp;&nbsp;&nbsp;&nbsp;&nbsp;&nbsp;&nbsp;&nbsp;&nbsp;&nbsp;&nbsp;&nbsp;&nbsp;&nbsp;&nbsp;&nbsp;&nbsp;&nbsp;&nbsp;&nbsp;&nbsp;&nbsp;&nbsp;&nbsp;&nbsp;&nbsp;&nbsp;&nbsp;&nbsp;&nbsp;&nbsp;&nbsp;&nbsp;&nbsp;&nbsp;&nbsp;&nbsp;&nbsp;&nbsp;&nbsp;&nbsp;&nbsp;&nbsp;&nbsp;&nbsp;<br />\nRE13067 Neubrandenburg ab 21:31 Uhr nach Neustrelitz&nbsp;&nbsp;&nbsp;&nbsp;&nbsp;</p>\n\n<p>RE13052 Neustrelitz ab 06:02 Uhr nach Neubrandenburg&nbsp;&nbsp;&nbsp;&nbsp;&nbsp;&nbsp;&nbsp;&nbsp;&nbsp;&nbsp;&nbsp;&nbsp;&nbsp;&nbsp;&nbsp;&nbsp;&nbsp;&nbsp;&nbsp;&nbsp;&nbsp;&nbsp;&nbsp;&nbsp;&nbsp;&nbsp;&nbsp;&nbsp;&nbsp;&nbsp;&nbsp;&nbsp;&nbsp;&nbsp;&nbsp;&nbsp;&nbsp;&nbsp;&nbsp;&nbsp;&nbsp;&nbsp;&nbsp;&nbsp;&nbsp;&nbsp;&nbsp;&nbsp;&nbsp;&nbsp;&nbsp;&nbsp;&nbsp;&nbsp;&nbsp;&nbsp;&nbsp;&nbsp;&nbsp;&nbsp;&nbsp;&nbsp;&nbsp;&nbsp;&nbsp;&nbsp;<br />\nRE13054 Neustrelitz ab 08:03 Uhr nach Neubrandenburg&nbsp;&nbsp;&nbsp;&nbsp;&nbsp;&nbsp;&nbsp;&nbsp;&nbsp;&nbsp;&nbsp;&nbsp;&nbsp;&nbsp;&nbsp;&nbsp;&nbsp;&nbsp;&nbsp;&nbsp;&nbsp;&nbsp;&nbsp;&nbsp;&nbsp;&nbsp;&nbsp;&nbsp;&nbsp;&nbsp;&nbsp;&nbsp;&nbsp;&nbsp;&nbsp;&nbsp;&nbsp;&nbsp;&nbsp;&nbsp;&nbsp;&nbsp;&nbsp;&nbsp;&nbsp;&nbsp;&nbsp;&nbsp;&nbsp;&nbsp;&nbsp;&nbsp;&nbsp;&nbsp;&nbsp;&nbsp;&nbsp;&nbsp;&nbsp;&nbsp;&nbsp;&nbsp;&nbsp;&nbsp;&nbsp;&nbsp;&nbsp;&nbsp;&nbsp;&nbsp;&nbsp;&nbsp;&nbsp;&nbsp;&nbsp;&nbsp;&nbsp;&nbsp;&nbsp;&nbsp;<br />\nRE13056 Neustrelitz ab 10:03 Uhr nach Neubrandenburg&nbsp;&nbsp;&nbsp;&nbsp;&nbsp;&nbsp;&nbsp;&nbsp;&nbsp;&nbsp;&nbsp;&nbsp;&nbsp;&nbsp;&nbsp;&nbsp;&nbsp;&nbsp;&nbsp;&nbsp;&nbsp;&nbsp;&nbsp;&nbsp;&nbsp;&nbsp;&nbsp;&nbsp;&nbsp;&nbsp;&nbsp;&nbsp;&nbsp;&nbsp;&nbsp;&nbsp;&nbsp;&nbsp;&nbsp;&nbsp;&nbsp;&nbsp;&nbsp;&nbsp;&nbsp;&nbsp;&nbsp;&nbsp;&nbsp;&nbsp;&nbsp;&nbsp;&nbsp;&nbsp;&nbsp;&nbsp;&nbsp;&nbsp;&nbsp;&nbsp;&nbsp;&nbsp;&nbsp;&nbsp;&nbsp;&nbsp;&nbsp;&nbsp;&nbsp;&nbsp;&nbsp;&nbsp;&nbsp;&nbsp;&nbsp;&nbsp;&nbsp;&nbsp;&nbsp;&nbsp;<br />\nRE13064 Neustrelitz ab 18:03 Uhr nach Neubrandenburg&nbsp;&nbsp;&nbsp;&nbsp;&nbsp;&nbsp;&nbsp;&nbsp;&nbsp;&nbsp;&nbsp;&nbsp;&nbsp;&nbsp;&nbsp;&nbsp;&nbsp;&nbsp;&nbsp;&nbsp;&nbsp;&nbsp;&nbsp;&nbsp;&nbsp;&nbsp;&nbsp;&nbsp;&nbsp;&nbsp;&nbsp;&nbsp;&nbsp;&nbsp;&nbsp;&nbsp;&nbsp;&nbsp;&nbsp;&nbsp;&nbsp;&nbsp;&nbsp;&nbsp;&nbsp;&nbsp;&nbsp;&nbsp;&nbsp;&nbsp;&nbsp;&nbsp;&nbsp;&nbsp;&nbsp;&nbsp;&nbsp;&nbsp;&nbsp;&nbsp;&nbsp;&nbsp;&nbsp;&nbsp;&nbsp;&nbsp;&nbsp;&nbsp;&nbsp;&nbsp;&nbsp;&nbsp;&nbsp;&nbsp;&nbsp;&nbsp;&nbsp;&nbsp;&nbsp;&nbsp;<br />\nRE13066 Neustrelitz ab 20:03 Uhr nach Neubrandenburg&nbsp;&nbsp;&nbsp;&nbsp;&nbsp;&nbsp;&nbsp;&nbsp;&nbsp;&nbsp;&nbsp;&nbsp;&nbsp;&nbsp;&nbsp;&nbsp;&nbsp;&nbsp;&nbsp;&nbsp;&nbsp;&nbsp;&nbsp;&nbsp;&nbsp;&nbsp;&nbsp;&nbsp;&nbsp;&nbsp;&nbsp;&nbsp;&nbsp;&nbsp;&nbsp;&nbsp;&nbsp;&nbsp;&nbsp;&nbsp;&nbsp;&nbsp;&nbsp;&nbsp;&nbsp;&nbsp;&nbsp;&nbsp;&nbsp;&nbsp;&nbsp;&nbsp;&nbsp;&nbsp;&nbsp;&nbsp;&nbsp;&nbsp;&nbsp;&nbsp;&nbsp;&nbsp;&nbsp;&nbsp;&nbsp;&nbsp;&nbsp;&nbsp;<br />\nRE13068 Neustrelitz ab 22:03 Uhr nach Neubrandenburg - Ausfall nur am 21.03.&nbsp;&nbsp;&nbsp;</p>\n\n<p>Bitte nutzen Sie die nachfolgenden Z&uuml;ge der Linie RE5 von/nach Stralsund und von/nach W&uuml;nsdorf(Waldstadt)/Elsterwerda.&nbsp; &nbsp; &nbsp; &nbsp; &nbsp; &nbsp; &nbsp; &nbsp; &nbsp; &nbsp; &nbsp; &nbsp; &nbsp; &nbsp; &nbsp; &nbsp; &nbsp; &nbsp; &nbsp; &nbsp; &nbsp; &nbsp; &nbsp; &nbsp; &nbsp; &nbsp; &nbsp; &nbsp; &nbsp; &nbsp; &nbsp; &nbsp; &nbsp; &nbsp;&nbsp;</p>\n\n<p><strong>Auf der Linie RE4 fallen vom 21. bis 23. M&auml;rz 2022 aus:</strong><br />\nRE13271&nbsp;Pasewalk ab 06:10 Uhr nach Ueckerm&uuml;nde Stadthafen<br />\nRE13273 Pasewalk ab 08:22 Uhr nach Ueckerm&uuml;nde&nbsp;Stadthafen<br />\nRE13275 Pasewalk ab 10:22 Uhr nach Ueckerm&uuml;nde&nbsp;Stadthafen<br />\nRE13277 Pasewalk ab 12:22 Uhr nach Ueckerm&uuml;nde Stadthafen&nbsp;&nbsp;&nbsp;&nbsp;&nbsp;&nbsp;&nbsp;&nbsp;&nbsp;&nbsp;&nbsp;&nbsp;&nbsp;&nbsp;&nbsp;&nbsp;&nbsp;&nbsp;&nbsp;&nbsp;&nbsp;&nbsp;&nbsp;&nbsp;&nbsp;&nbsp;&nbsp;&nbsp;&nbsp;&nbsp;&nbsp;&nbsp;&nbsp;&nbsp;&nbsp;&nbsp;&nbsp;&nbsp;&nbsp;&nbsp;<br />\nRE13279 Pasewalk ab 14:22 Uhr nach Ueckerm&uuml;nde Stadthafen&nbsp;&nbsp;&nbsp;&nbsp;&nbsp;&nbsp;&nbsp;&nbsp;&nbsp;&nbsp;&nbsp;&nbsp;&nbsp;&nbsp;&nbsp;&nbsp;&nbsp;&nbsp;&nbsp;&nbsp;&nbsp;&nbsp;&nbsp;&nbsp;&nbsp;&nbsp;&nbsp;&nbsp;&nbsp;&nbsp;&nbsp;&nbsp;&nbsp;&nbsp;&nbsp;&nbsp;&nbsp;&nbsp;&nbsp;&nbsp;&nbsp;&nbsp;&nbsp;&nbsp;&nbsp;&nbsp;&nbsp;&nbsp;<br />\nRE13281 Pasewalk ab 16:08 Uhr nach Ueckerm&uuml;nde Stadthafen&nbsp; &nbsp; &nbsp; &nbsp; &nbsp; &nbsp; &nbsp; &nbsp; &nbsp; &nbsp; &nbsp; &nbsp; &nbsp; &nbsp; &nbsp; &nbsp; &nbsp; &nbsp; &nbsp; &nbsp; &nbsp; &nbsp; &nbsp; &nbsp; &nbsp; &nbsp; &nbsp; &nbsp; &nbsp; &nbsp; &nbsp; &nbsp; &nbsp;&nbsp;<br />\nRE13283 Pasewalk ab18:22 Uhr nach Ueckerm&uuml;nde Stadthafen&nbsp;&nbsp;&nbsp;&nbsp;&nbsp;&nbsp;&nbsp;&nbsp;&nbsp;&nbsp;&nbsp;&nbsp;&nbsp;&nbsp;&nbsp;&nbsp;&nbsp;&nbsp;&nbsp;&nbsp;&nbsp;&nbsp;&nbsp;&nbsp;&nbsp;&nbsp;&nbsp;&nbsp;&nbsp;&nbsp;&nbsp;&nbsp;&nbsp;&nbsp;&nbsp;&nbsp;&nbsp;&nbsp;&nbsp;&nbsp;&nbsp;&nbsp;&nbsp;&nbsp;&nbsp;&nbsp;&nbsp;&nbsp;&nbsp;&nbsp;&nbsp;&nbsp;&nbsp;&nbsp;&nbsp;&nbsp;&nbsp;&nbsp;&nbsp;&nbsp;&nbsp;&nbsp;&nbsp;&nbsp;&nbsp;&nbsp;&nbsp;&nbsp;<br />\nRE13285&nbsp;Pasewalk ab20:22 Uhr nach Ueckerm&uuml;nde Stadthafen&nbsp; &nbsp; &nbsp; &nbsp; &nbsp; &nbsp; &nbsp; &nbsp; &nbsp; &nbsp; &nbsp; &nbsp; &nbsp; &nbsp; &nbsp; &nbsp; &nbsp; &nbsp; &nbsp; &nbsp; &nbsp; &nbsp; &nbsp; &nbsp; &nbsp; &nbsp;</p>\n\n<p>RE13270 Ueckerm&uuml;nde Stadthafen ab 07:00 Uhr nach&nbsp;Pasewalk&nbsp;<br />\nRE13272 Ueckerm&uuml;nde Stadthafen ab 09:00 Uhr nach Pasewalk<br />\nRE13274 Ueckerm&uuml;nde Stadthafen ab 11:00 Uhr nach&nbsp;Pasewalk<br />\nRE13276 Ueckerm&uuml;nde Stadthafen ab 13:00 Uhr nach Pasewalk<br />\nRE13278 Ueckerm&uuml;nde Stadthafen ab 15:00 Uhr nach Pasewalk&nbsp;&nbsp;&nbsp;&nbsp;&nbsp;&nbsp;&nbsp;&nbsp;&nbsp;&nbsp;&nbsp;&nbsp;&nbsp;&nbsp;&nbsp;&nbsp;&nbsp;&nbsp;&nbsp;&nbsp;&nbsp;&nbsp;&nbsp;&nbsp;&nbsp;&nbsp;&nbsp;&nbsp;&nbsp;&nbsp;&nbsp;&nbsp;&nbsp;&nbsp;&nbsp;&nbsp;&nbsp;&nbsp;&nbsp;&nbsp;&nbsp;&nbsp;&nbsp;&nbsp;&nbsp;&nbsp;&nbsp;&nbsp;&nbsp;&nbsp;&nbsp;&nbsp;<br />\nRE13280 Ueckerm&uuml;nde Stadthafen ab 17:00 Uhr nach Pasewalk&nbsp;<br />\nRE13282 Ueckerm&uuml;nde Stadthafen ab 19:00 Uhr nach Pasewalk<br />\nRE13284 Ueckerm&uuml;nde Stadthafen ab 21:00 Uhr nach Pasewalk<br />\n<br />\nBitte nutzen Sie als Ersatz den bereitgestellten Ersatzverkehr.</p>\n\n<p><strong>Auf der Linie S1 fallen vom 22. bis 25.03. aus:</strong><br />\nS33916 Rostock ab 13:25 Uhr nach Warnem&uuml;nde<br />\nS33924 Rostock ab 14:25 Uhr nach Warnem&uuml;nde<br />\nS33917 Warnem&uuml;nde ab 13:56 Uhr nach Rostock<br />\nS33925 Warnem&uuml;nde ab 14:54 Uhr nach Rostock</p>\n",
        "linkDataList": [
          {
            "link": "https://assets.static-bahn.de/dam/jcr:0c79c382-fc7e-4e15-9d84-a8738394630e/Busnotverkehr%20RB17%20vom%2019.-23.03.2022.pdf",
            "title": "Ersatzverkehr RB17 (PDF, 76 KB)",
            "info": "",
            "openInNewTab": false
          },
          {
            "link": "https://assets.static-bahn.de/dam/jcr:b2336f23-0238-4334-9744-7f7954785744/Ersatzverkehr%20RE4%2021.-23.03.2022.pdf",
            "title": "Ersatzverkehr RE4 (PDF, 80 KB)",
            "info": "",
            "openInNewTab": false
          }
        ]
      },
      "closingText": "<p>Bitte informieren Sie sich unmittelbar vor Reiseantritt &uuml;ber Ihre tats&auml;chlichen Abfahrts- und Ankunftszeiten in der Reiseauskunft unter <a href=\"https://www.bahn.de/\">bahn.de/reiseauskunft</a>, in der App&nbsp;<a href=\"https://www.bahn.de/service/mobile/streckenagent-app\" target=\"_blank\">DB Streckenagent</a>&nbsp;und im&nbsp;<a href=\"https://www.bahn.de/service/mobile/db-navigator\" target=\"_blank\">DB Navigator</a>&nbsp;oder pers&ouml;nlich unter <a href=\"tel:03312356881 \">0331 235 6881 </a>und<a href=\"tel: 0385 750 2405 \">&nbsp;0385 750 2405</a>.&nbsp; &nbsp;&nbsp; &nbsp; &nbsp; &nbsp; &nbsp; &nbsp; &nbsp; &nbsp; &nbsp; &nbsp;</p>\n",
      "priority": "0",
      "distance": [
        "regional"
      ],
      "areas": [
        "mv"
      ],
      "lastModified": "22.03.2022 07:21",
      "author": "nordost",
      "expand": false,
      "priorityValue": 101
    },
    {
      "id": "7bd917b2-dc6a-45e7-af58-f4cc20fdb5a7",
      "headline": "Unwetterschäden an der Ahr und in der Eifel ",
      "newsType": "Unwetterschäden",
      "introText": "<p>Informationen &uuml;ber die Auswirkungen auf den Bahnverkehr durch die Unwettersch&auml;den an der Ahr und in der Eifel finden Sie&nbsp;<a href=\"http://www.zuginfo.nrw\">hier</a></p>\n",
      "connections": [
        ""
      ],
      "priority": "0",
      "distance": [
        "regional"
      ],
      "areas": [
        "rp"
      ],
      "lastModified": "04.11.2021 10:10",
      "expand": false,
      "priorityValue": 101
    },
    {
      "id": "f7f32c50-0333-446b-ad64-314caf06fac2",
      "headline": "Meldungen der DB Regio NRW",
      "newsType": "Betriebslage",
      "timePeriod": "unbefristet",
      "introText": "<p>Meldungen &uuml;ber die aktuelle Betriebslage der DB Regio NRW finden Sie&nbsp;<a href=\"http://www.zuginfo.nrw\" target=\"_blank\">hier</a></p>\n\n<p>&nbsp;</p>\n\n<p>Aktuelle Verkehrsmeldungen und Infos der DB Regio NRW finden Sie auf dem frei zug&auml;nglichen&nbsp;<a href=\"http://www.twitter.com/Regio_NRW\" target=\"_blank\">Twitter-Kanal</a></p>\n",
      "connections": [],
      "priority": "0",
      "distance": [
        "regional"
      ],
      "areas": [
        "nw"
      ],
      "lastModified": "04.11.2021 10:10",
      "author": "nrw",
      "expand": true,
      "priorityValue": 101
    },
    {
      "id": "1d3241f6-b686-4f6f-b90b-1f50d24644e7",
      "headline": "Keine Zugfahrten zwischen Bad Dürkheim und Freinsheim",
      "newsType": "Bauarbeiten",
      "timePeriod": "bis voraussichtlich 22.05.2022",
      "introText": "<p>Wegen der&nbsp;erforderlichen&nbsp;Bauarbeiten nach Unwettersch&auml;den und der&nbsp;zus&auml;tzlichen Unterh&ouml;hlung des Gleises durch Dachsbauten bleibt die Strecke zwischen Bad D&uuml;rkheim und Freinsheim leider weiterhin f&uuml;r den Bahnverkehr komplett gesperrt.</p>\n",
      "connections": [
        "RB45: Neustadt/Wstr - Bad Dürkheim - Freinsheim - Grünstadt"
      ],
      "download": {
        "text": "<p>Die Z&uuml;ge zwischen Neustadt(Wstr) Hbf und Freinsheim verkehren nur zwischen Neustadt(Wstr)Hbf und Bad D&uuml;rkheim und entfallen zwischen Bad D&uuml;rkheim und Freinsheim.</p>\n\n<p>Die Z&uuml;ge zwischen Neustadt(Wstr) Hbf und Gr&uuml;nstadt verkehren nur zwischen Neustadt(Wstr)Hbf und Bad D&uuml;rkheim sowie zwischen Gr&uuml;nstadt und Freinsheim.</p>\n\n<p>Ein Schienenersatzverkehr mit Bussen zwischen Bad D&uuml;rkheim und Freinsheim/Gr&uuml;nstadt ist eingerichtet. Informationen zu Ihren Fahrtm&ouml;glichkeiten&nbsp;entnehmen&nbsp;Sie bitte der Reiseauskunft unter&nbsp;<a href=\"https://www.bahn.de/\">www.bahn.de</a></p>\n\n<p>Nach aktuellem Stand soll die Streckensperrung noch bis voraussichtlich 22. Mai 2022 andauern.</p>\n"
      },
      "closingText": "<p>Bitte rechnen Sie f&uuml;r die Dauer der Sperrung auf jeden Fall mehr Reisezeit ein und pr&uuml;fen Sie Ihre Reiseverbindung noch einmal unmittelbar vor Fahrtantritt unter <a href=\"http://www.bahn.de\" target=\"_blank\"><strong>www.bahn.de</strong></a>&nbsp;, <a href=\"http://www.bahn.de/ris\" target=\"_blank\"><strong>www.bahn.de/ris</strong></a> mit mobilen Endger&auml;ten unter <a href=\"http://mobile.bahn.de\" target=\"_blank\"><strong>mobile.bahn.de</strong></a>&nbsp;oder der&nbsp;<a href=\"http://www.bahn.de/p/view/service/buchung/mobil/db-navigator.shtm\" target=\"_blank\"><strong>DB Navigator-App</strong></a>.</p>\n\n<p>Weitere Informationen erhalten Sie auch &uuml;ber die App <a href=\"http://www.bahn.de/p/view/service/buchung/mobil/streckenagent-app.shtml\" target=\"_blank\"><strong>DB-Streckenagent</strong></a> oder auf <a href=\"http://www.twitter.com/Regio_Mitte\" target=\"_blank\"><strong>twitter.com/regio_mitte</strong></a>.</p>\n\n<p>F&uuml;r die Ihnen entstehenden Unannehmlichkeiten bitten wir um Entschuldigung und hoffen auf Ihr Verst&auml;ndnis.</p>\n\n<p>DB Regio AG, Region Mitte</p>\n",
      "priority": "0",
      "distance": [
        "regional"
      ],
      "areas": [
        "rp"
      ],
      "lastModified": "21.02.2022 09:04",
      "author": "mitte",
      "expand": false,
      "priorityValue": 101
    },
    {
      "id": "0b3fbf14-d456-4c39-ba7a-41fa7b5ca467",
      "headline": "Meldungen der DB Regio Bayern",
      "newsType": "Störungen",
      "timePeriod": "unbefristet",
      "introText": "<p>Meldungen &uuml;ber die <strong>aktuelle Betriebslage 24/7 des Regionalverkehrs in Bayern</strong> finden Sie auf den folgenden Seiten:</p>\n",
      "connections": [],
      "internal": {
        "linkDataList": [
          {
            "link": "https://regional.bahn.de/regionen/bayern/fahrplan/aktuelle_betriebslage",
            "title": "Meldungen der DB Regio Bayern",
            "info": "",
            "openInNewTab": true
          },
          {
            "link": "https://www.s-bahn-muenchen.de/fahren/betriebslage",
            "title": "Meldungen der S-Bahn München",
            "info": "",
            "openInNewTab": true
          }
        ]
      },
      "closingText": "<p>Bitte informieren Sie sich regelm&auml;&szlig;ig vor Abfahrt auch in der&nbsp;<strong><a href=\"https://www.bahn.de/service/mobile/streckenagent-app\" target=\"_blank\">DB Streckenagent</a> oder <a href=\"https://www.bahn.de/service/mobile/db-navigator\" target=\"_blank\">DB Navigator</a> App&nbsp;</strong>&uuml;ber Ihre Verbindung.&nbsp;</p>\n\n<p><strong>Verkehrsmeldungen 24/7</strong> finden Sie auch auf unseren <strong>Twitter-Kan&auml;len</strong>:&nbsp;</p>\n\n<p><a href=\"https://twitter.com/streckenagent_M\" target=\"_blank\">Streckenagent S-Bahn M&uuml;nchen</a></p>\n\n<p><a href=\"https://twitter.com/streckenagent_N\" target=\"_blank\">Streckenagent S-Bahn N&uuml;rnberg</a>&nbsp;</p>\n\n<p><a href=\"https://twitter.com/streckenagentAS\" target=\"_blank\">Streckenagent Allg&auml;u-Schwaben</a></p>\n\n<p><a href=\"https://twitter.com/streckenagentOB\" target=\"_blank\">Streckenagent Oberbayern</a></p>\n\n<p><a href=\"https://twitter.com/streckenagentFR\" target=\"_blank\">Streckenagent Franken</a>&nbsp;</p>\n\n<p><a href=\"https://twitter.com/streckenagentNB\" target=\"_blank\">Streckenagent Nordostbayern</a>&nbsp;</p>\n",
      "priority": "0",
      "distance": [
        "regional"
      ],
      "areas": [
        "by"
      ],
      "lastModified": "01.03.2022 14:42",
      "author": "bayern",
      "expand": true,
      "priorityValue": 101
    },
    {
      "id": "8e0b9fc7-d8d6-42b4-a543-23d179b52e55",
      "headline": "Veränderter Fahrplan auf der Schwarzwaldbahn",
      "newsType": "Untersuchung an mehreren Zügen",
      "timePeriod": "Seit Mittwoch, 16. März bis voraussichtlich Sonntag, 3. April 2022",
      "introText": "<p>Die Regional-Express-Z&uuml;ge (RE) fahren in einem vor&uuml;bergehend reduzierten, aber verl&auml;sslichen Grundtakt: Zwischen Konstanz und Offenburg alle zwei Stunden, zwischen Offenburg und Karlsruhe st&uuml;ndlich. Im wichtigen Verkehr f&uuml;r Sch&uuml;ler:innen und Pendler:innen bleibt der Fahrplan wie gewohnt. Dazu setzt die DB zum Teil auch Busse ein.&nbsp;<strong>Am 22. M&auml;rz k&ouml;nnen Sie die ICE/IC/EC zwischen Offenburg und Karlsruhe auch mit Fahrkarten des Nahverkehrs nutzen.</strong></p>\n\n<p>An den Wochenenden jeweils von Freitag, 21 Uhr bis Montag, 1 Uhr, ist die Strecke zwischen Engen und Singen (Hohentwiel) wegen Bauarbeiten gesperrt.&nbsp;Die Regional-Express-Z&uuml;ge (RE) fallen zwischen Engen und Konstanz aus. Zwischen Engen und Singen (Hohentwiel) fahren Busse. Zwischen Singen (Hohentwiel) und Konstanz fahren die Z&uuml;ge des Seehas.</p>\n",
      "connectionsHeadline": "Betroffene Linie:",
      "connections": [
        "RE 2 Karlsruhe Hbf - Offenburg - Konstanz"
      ],
      "download": {
        "linkDataList": [
          {
            "link": "https://assets.static-bahn.de/dam/jcr:f047d103-3761-4790-acce-4821ac92bfb5/KBS_720_SWB_18.03_Mo-Fr_Stand_180322.pdf",
            "title": "Zugverkehr Linie RE 2 (Schwarzwaldbahn) Montag-Freitag (PDF, 444 KB)",
            "info": "",
            "openInNewTab": false
          },
          {
            "link": "https://assets.static-bahn.de/dam/jcr:41b4ff22-db64-41e6-894e-e6c93739d332/KBS_720_SWB_18.03_Sa-So_Stand_180322.pdf",
            "title": "Zugverkehr Linie RE 2 (Schwarzwaldbahn) Samstag-Sonntag (PDF, 458 KB)",
            "info": "",
            "openInNewTab": false
          }
        ]
      },
      "closingText": "<p>Der ver&auml;nderte Fahrplan ist ab Mittwoch, 23. M&auml;rz in die Reiseauskunft auf bahn.de und der DB Navigator APP eingearbeitet.</p>\n\n<p>Immer sofort informiert &uuml;ber St&ouml;rungen, Ersatzverkehr und Alternativrouten. Denn Ihren mobilen Zugbegleiter haben Sie mit der neuen <strong><a href=\"https://www.bahn.de/p/view/service/mobile/streckenagent-app.shtml\" target=\"_blank\">Streckenagent-APP</a></strong> immer dabei!</p>\n",
      "priority": "0",
      "distance": [
        "regional"
      ],
      "areas": [
        "bw"
      ],
      "lastModified": "22.03.2022 05:49",
      "author": "baden_wuerttemberg",
      "expand": false,
      "priorityValue": 101
    },
    {
      "id": "383694eb-19ec-48c4-901a-af32d1359f91",
      "headline": "Vorübergehend reduziertes Fahrplanangebot auf dem Hochrhein",
      "newsType": "erhöhter Krankenstand beim Fahrpersonal",
      "timePeriod": "ab 18. März bis vsl. 25. März 2022",
      "introText": "<p>DB Regio Baden-W&uuml;rttemberg hat das Fahrplangebot auf dem Hochrhein zwischen Basel Bad Bf - Waldshut - Erzingen(Baden) bzw. St&uuml;hlingen reduziert.</p>\n\n<p>Die Z&uuml;ge der Linie RB 37 zwischen Waldshut und St&uuml;hlingen verkehren ab dem 23. M&auml;rz wieder regul&auml;r. Der Ersatzverkehr mit Bus wird auf diesem Abschnitt eingestellt.</p>\n",
      "connectionsHeadline": "Betroffene Linien:",
      "connections": [
        "RB 35: Basel - Waldshut - Erzingen(Baden)",
        "RB 37: Waldshut - Stühlingen"
      ],
      "download": {
        "text": "<p>Die reduzierten Fahrpl&auml;ne finden Sie hier als PDF-Datei im Anhang und in den digitalen Auskunftsmedien wie z.B. bahn.de, DB Navigator, <a href=\"https://www.bahn.de/p/view/service/mobile/streckenagent-app.shtml\">DB Streckenagent</a>.</p>\n",
        "linkDataList": [
          {
            "link": "https://assets.static-bahn.de/dam/jcr:61e58f04-2cd2-46d6-b516-6595a26f5da5/Fahrplan_Basel-Singen_Stand_180322.pdf",
            "title": "Ersatzfahrplan Hochrhein (PDF, 595 KB)",
            "info": "",
            "openInNewTab": false
          }
        ]
      },
      "closingText": "<p>Sollte sich die Lage zwischenzeitlich stabilisieren, werden wir schnellstm&ouml;glich zum normalen Fahrplanangebot zur&uuml;ckkehren.</p>\n\n<p>Bitte ber&uuml;cksichtigen Sie die &Auml;nderungen im Zugverkehr bei Ihrer Reiseplanung und rechnen Sie f&uuml;r die Dauer der Beeintr&auml;chtigung mehr Reisezeit ein.</p>\n",
      "priority": "0",
      "distance": [
        "regional"
      ],
      "areas": [
        "bw"
      ],
      "lastModified": "22.03.2022 12:59",
      "author": "baden_wuerttemberg",
      "expand": false,
      "priorityValue": 101
    },
    {
      "id": "7b6a1459-3d4f-4b3c-b583-7b07ca10c8ad",
      "headline": "Zusätzliche Busse zum Schüler- und Berufsverkehr",
      "newsType": "Kapazitätssteigerung",
      "timePeriod": "an Schul- und Werktagen",
      "introText": "<p>Die DB Regio AG Baden-W&uuml;rttemberg setzt wieder zus&auml;tzliche Verst&auml;rkerbusse von Montag bis Freitag f&uuml;r&nbsp;den Sch&uuml;ler- und Berufsverkehr ein. Durch den Einsatz der zus&auml;tzlich verkehrenden Busse wird die Kapazit&auml;t nochmals erh&ouml;ht werden. Die Abfahrtszeiten der Unterwegshalte finden sie in der Fahrplanauskunft z.B. unter <a href=\"https://www.bahn.de/\" target=\"_blank\"><strong>www.bahn.de</strong></a></p>\n",
      "connections": [],
      "closingText": "<p>Die meist parallel zu den Z&uuml;gen verkehrenden Busse starten wie folgt:</p>\n\n<p><strong>Hochschwarzwald:</strong><br />\n-&nbsp;L&ouml;ffingen - Neustadt/Schwarzwald mit Abfahrt 07:07 Uhr in L&ouml;ffingen<br />\n- Titisee - Neustadt(Schwarzw) mit Abfahrt 07:14 Uhr in Titisee</p>\n\n<p><strong>Kaiserstuhl:</strong><br />\n-&nbsp;Eichstetten Bahnhof -&nbsp;B&ouml;tzingen - Gottenheim - Freiburg Bissierstr. - Freiburg Robert-Koch-Str, Freiburg ZOB mit Abfahrt 7:10 Uhr in Eichstetten</p>\n\n<p><strong>Hochrhein:</strong><br />\n- Bietingen - Gottmadingen - Singen Anton-Bruckner-Str. - Singen (Htw) Bahnhof Bandoleros mit Abfahrt 07:15 Uhr in Bietingen<br />\n-&nbsp;&nbsp;Gottmadingen - Singen Anton-Bruckner-Str. - Singen (Htw) Bahnhof Bandoleros mit Abfahrt 07:20 Uhr in Gottmadingen<br />\n- Singen (Htw) Maggi - Gottmadingen Bf mit Abfahrt 13:06 Uhr in Singen<br />\n-&nbsp;Singen (Htw) Maggi - Gottmadingen Bf - Bietingen Bf mit Abfahrt 13:36 Uhr in Singen</p>\n\n<p><strong>Raum Neckar-Alb:&nbsp;</strong><br />\n- Metzingen Busbahnhof - Metzingen-Neuhausen Insel - Dettingen (Erms) Lehen Bushaltestelle - Dettingen (Erms) Mitte Bahnhof - Dettingen (Erms) Freibad Bushaltestelle - Dettingen (Erms) Gsaidt Bushaltestelle - Bad Urach Wasserfall Bushaltestelle - Bad Urach Busbahnhof mit Abfahrt 07:12 Uhr in Metzingen<br />\n- T&uuml;bingen Hbf, Bushaltestelle Neckaraue, Kirchentellinsfurt Bahnhof, Bushaltestelle Sigel-Stuben, Ersatzhaltestelle Schulbus Olgastra&szlig;e, Bushaltestelle Westbahnhof, Reutlingen Hbf Bahnhofstra&szlig;e, Bushaltestelle Am Heilbrunnen, Metzingen Bahnhof mit Abfahrt 06:31 Uhr in T&uuml;bingen Hbf</p>\n\n<p><strong>Gro&szlig;raum Ulm:&nbsp;</strong><br />\n-&nbsp;Schemmerberg Bf - Warthausen Rathaus - Biberach(Ri&szlig;) Bhf - Biberach Schulzentrum - Biberach Liebherr/B465 mit Abfahrt 07:00 Uhr in Schemmerberg<br />\n&nbsp;</p>\n\n<p><strong>Raum Bodensee:&nbsp;&nbsp;</strong><br />\n-&nbsp;Kressbronn Bahnhof - Langenargen Bahnhof - Langenargen Bahnhof - Friedrichshafen Jugendherberge - Friedrichshafen Stadtbahnhof - Friedrichshafen Jugendherberge mit Abfahrt 06:53 Uhr in Kressbronn<br />\n-&nbsp;Kressbronn Bahnhof - Langenargen Bahnhof - Eriskirch Irisstra&szlig;e - Friedrichshafen Jugendherberge - Friedrichshafen Stadtbahnhof - Friedrichshafen Jugendherberge mit Abfahrt 07:29 Uhr in Kressbronn<br />\n-&nbsp;Kressbronn, Bahnhof - Langenargen Bahnhof - Eriskirch Irisstra&szlig;e - Friedrichshafen Jugendherberge - Friedrichshafen Stadtbahnhof - Friedrichshafen Schulzentrum mit Abfahrt 07:57 Uhr in Kressbronn</p>\n\n<p>Immer sofort informiert &uuml;ber St&ouml;rungen, Ersatzverkehr und Alternativrouten. Denn Ihren mobilen Zugbegleiter haben Sie mit der neuen <a href=\"https://www.bahn.de/service/mobile/streckenagent-app\" target=\"_blank\"><strong>Streckenagent-App</strong></a>&nbsp;immer dabei!</p>\n",
      "priority": "0",
      "distance": [
        "regional"
      ],
      "areas": [
        "bw"
      ],
      "lastModified": "07.03.2022 00:32",
      "author": "baden_wuerttemberg",
      "expand": false,
      "priorityValue": 101
    },
    {
      "id": "67d9e854-390f-401c-a4ef-45fa289d069c",
      "headline": "Meldungen der S-Bahn Stuttgart",
      "newsType": "Betriebslage",
      "timePeriod": "unbefristet",
      "introText": "<p>Meldungen &uuml;ber die aktuelle Betriebslage im S-Bahnverkehr in Stuttgart finden Sie auf:<br />\n<a href=\"https://www.s-bahn-stuttgart.de/s-stuttgart/betriebslage-4097192\" target=\"_blank\">Betriebslage S-Bahn Stuttgart</a><br />\n<a href=\"https://twitter.com/SBahn_Stuttgart\" target=\"_blank\">Twitter-Kanal</a></p>\n",
      "connections": [],
      "priority": "0",
      "distance": [
        "regional"
      ],
      "areas": [
        "bw"
      ],
      "lastModified": "20.12.2021 22:37",
      "author": "baden_wuerttemberg",
      "expand": true,
      "priorityValue": 101
    }
  ],
  "filter": {
    "areas": [
      "bw",
      "by",
      "be",
      "br",
      "hb",
      "hh",
      "he",
      "mv",
      "ni",
      "nw",
      "rp",
      "sl",
      "sn",
      "st",
      "sh",
      "th"
    ],
    "distance": [
      "regional",
      "longDistance"
    ]
  }
}
